onlinecourses_ooo/__init__.py
onlinecourses_ooo/onlinecourses_ooo.py
onlinecourses_ooo-0.1.0b2.dist-info/DESCRIPTION.rst
onlinecourses_ooo-0.1.0b2.dist-info/METADATA
onlinecourses_ooo-0.1.0b2.dist-info/RECORD
onlinecourses_ooo-0.1.0b2.dist-info/WHEEL
onlinecourses_ooo-0.1.0b2.dist-info/entry_points.txt
onlinecourses_ooo-0.1.0b2.dist-info/metadata.json
onlinecourses_ooo-0.1.0b2.dist-info/top_level.txt
