Metadata-Version: 2.0
Name: onlinecourses-ooo
Version: 0.1.0b2
Summary: My personal scraper for https://onlinecourses.ooo
Home-page: https://github.com/yujinyuz/onlinecourses-ooo
Author: Eugene Essun Oliveros
Author-email: jinyuzprodigy@gmail.com
License: MIT license
Keywords: onlinecourses_ooo
Platform: UNKNOWN
Classifier: Development Status :: 4 - Beta
Classifier: Intended Audience :: Developers
Classifier: Intended Audience :: Education
Classifier: Intended Audience :: End Users/Desktop
Classifier: License :: OSI Approved :: MIT License
Classifier: Natural Language :: English
Classifier: Programming Language :: Python :: 3.3
Classifier: Programming Language :: Python :: 3.4
Classifier: Programming Language :: Python :: 3.5
Classifier: Topic :: Software Development :: Version Control :: Git
Requires-Dist: beautifulsoup4
Requires-Dist: docopt
Requires-Dist: lxml
Requires-Dist: requests
